getignore.py
getignore3-3.5.3.dist-info/LICENSE
getignore3-3.5.3.dist-info/METADATA
getignore3-3.5.3.dist-info/WHEEL
getignore3-3.5.3.dist-info/entry_points.txt
getignore3-3.5.3.dist-info/RECORD
