Metadata-Version: 2.3
Name: getignore3
Version: 3.5.3
Summary: A tool to fetch and manage `.gitignore` templates from GitHub with minimal effort
Author: ashkanfeyzollahi@gmail.com
Author-email: ashkanfeyzollahi@gmail.com
Requires-Python: >=3.8
Classifier: Programming Language :: Python :: 3
Classifier: Programming Language :: Python :: 3.8
Classifier: Programming Language :: Python :: 3.9
Classifier: Programming Language :: Python :: 3.10
Classifier: Programming Language :: Python :: 3.11
Classifier: Programming Language :: Python :: 3.12
Classifier: Programming Language :: Python :: 3.13
Requires-Dist: appdirs (>=1.4.4,<2.0.0)
Requires-Dist: requests (>=2.32.4,<3.0.0)
Project-URL: Repository, https://github.com/ashkanfeyzollahi/getignore3
